kaindall_template/__init__.py
kaindall_template/example1.py
kaindall_template/example2.py
kaindall_template-0.0.1.dist-info/METADATA
kaindall_template-0.0.1.dist-info/WHEEL
kaindall_template-0.0.1.dist-info/top_level.txt
kaindall_template-0.0.1.dist-info/RECORD
