Metadata-Version: 2.1
Name: kaindall-template
Version: 0.0.1
Summary: This is a package to do the project of DIO's bootcamp
Home-page: UNKNOWN
Author: Kaindall
Author-email: gustavozanete2@gmail.com
License: UNKNOWN
Platform: UNKNOWN
Requires-Python: >=3.8
